CHANGES.txt
MANIFEST.in
README.rst
requirements.txt
setup.cfg
setup.py
agamemnon/__init__.py
agamemnon/cassandra.py
agamemnon/delegate.py
agamemnon/exceptions.py
agamemnon/factory.py
agamemnon/graph_constants.py
agamemnon/memory.py
agamemnon/primitives.py
agamemnon/rdf_store.py
agamemnon.egg-info/PKG-INFO
agamemnon.egg-info/SOURCES.txt
agamemnon.egg-info/dependency_links.txt
agamemnon.egg-info/not-zip-safe
agamemnon.egg-info/requires.txt
agamemnon.egg-info/top_level.txt
agamemnon/plugins/__init__.py
agamemnon/plugins/elasticsearch.py
agamemnon/tests/__init__.py
agamemnon/tests/test_rdf.py
agamemnon/tests/unit_tests.py
bin/generate_indices