Metadata-Version: 1.0
Name: agamemnon
Version: 0.4.0
Summary: A graph database built on top of cassandra
Home-page: https://github.com/globusonline/agamemnon
Author: Tom Howe
Author-email: trhowe@ci.uchicago.edu
License: LICENSE.txt
Keywords: cassandra
Platform: UNKNOWN
Classifier: Programming Language :: Python
